LICENSE
README.md
setup.py
easypypi/__init__.py
easypypi/classifiers.py
easypypi/easypypi.ico
easypypi/easypypi.py
easypypi/init_template.py
easypypi/licenses.json
easypypi/licenses.py
easypypi/readme_template.md
easypypi/script_template.py
easypypi/setup_template.py
easypypi/shared_functions.py
easypypi/test_template.py
easypypi/utils.py
easypypi.egg-info/PKG-INFO
easypypi.egg-info/SOURCES.txt
easypypi.egg-info/dependency_links.txt
easypypi.egg-info/requires.txt
easypypi.egg-info/top_level.txt