Metadata-Version: 2.1
Name: easypypi
Version: 2.0.7
Summary: By FAR the easiest and quickest way to publish your Python creations on PyPI so other people can just `pip install your_script`.
Home-page: https://github.com/Pfython/easypypi
Download-URL: https://github.com/Pfython/easypypi/archive/2.0.7.tar.gz
Author: Peter Fison
Author-email: peter@southwestlondon.tv
License: MIT License
Keywords: easypypi,Peter Fison,Pfython,pip,package,publish,share,build,deploy,Python
Platform: UNKNOWN
Classifier: Development Status :: 5 - Production/Stable
Classifier: Intended Audience :: Developers
Classifier: Operating System :: OS Independent
Classifier: Programming Language :: Python :: 3.6
Classifier: Programming Language :: Python :: 3.7
Classifier: Programming Language :: Python :: 3.8
Classifier: Programming Language :: Python :: 3.9
Classifier: Topic :: Documentation
Classifier: Topic :: Software Development
Classifier: Topic :: Software Development :: Build Tools
Classifier: Topic :: Software Development :: Documentation
Classifier: Topic :: Software Development :: Libraries :: Python Modules
Classifier: Topic :: Software Development :: Version Control
Classifier: Topic :: Software Development :: Version Control :: Git
Classifier: Topic :: System :: Archiving :: Packaging
Classifier: Topic :: System :: Installation/Setup
Classifier: Topic :: System :: Software Distribution
Classifier: Topic :: Utilities
Classifier: License :: OSI Approved :: MIT License
License-File: LICENSE
